[{"id":26,"isDeleted":0,"customerName":"测试客户","customerAge":66,"customerSex":1,"idCard":"210102196005010001","roomNo":"101","buildingNo":"606","checkinDate":1779984512309,"expirationDate":1811433600000,"contactTel":"13900139001","bedId":25,"psychosomaticState":"非常好","attention":"无过敏史","birthday":-305193600000,"height":"170","weight":"65","bloodType":"A","filepath":null,"userId":-1,"levelId":null,"familyMember":"儿子-张三"},{"id":33,"isDeleted":0,"customerName":"测试客户","customerAge":66,"customerSex":1,"idCard":"210102196005010001","roomNo":"101","buildingNo":"606","checkinDate":1780128060490,"expirationDate":1811433600000,"contactTel":"13900139001","bedId":32,"psychosomaticState":"良好","attention":"无过敏史","birthday":-305193600000,"height":"170","weight":"65","bloodType":"A","filepath":null,"userId":-1,"levelId":null,"familyMember":"儿子-张三"},{"id":40,"isDeleted":0,"customerName":"测试客户","customerAge":66,"customerSex":1,"idCard":"210102196005010001","roomNo":"101","buildingNo":"606","checkinDate":1780138739500,"expirationDate":1811433600000,"contactTel":"13900139001","bedId":39,"psychosomaticState":"良好","attention":"无过敏史","birthday":-305193600000,"height":"170","weight":"65","bloodType":"A","filepath":null,"userId":-1,"levelId":null,"familyMember":"儿子-张三"}]